LICENSE.txt
README.txt
setup.py
src/docs/HISTORY.txt
src/docs/INSTALL.txt
src/docs/LICENSE.GPL
src/docs/LICENSE.txt
src/getpaid/__init__.py
src/getpaid.pagseguro.egg-info/PKG-INFO
src/getpaid.pagseguro.egg-info/SOURCES.txt
src/getpaid.pagseguro.egg-info/dependency_links.txt
src/getpaid.pagseguro.egg-info/namespace_packages.txt
src/getpaid.pagseguro.egg-info/not-zip-safe
src/getpaid.pagseguro.egg-info/requires.txt
src/getpaid.pagseguro.egg-info/top_level.txt
src/getpaid/pagseguro/__init__.py
src/getpaid/pagseguro/configure.zcml
src/getpaid/pagseguro/i18n.sh
src/getpaid/pagseguro/interfaces.py
src/getpaid/pagseguro/overrides.zcml
src/getpaid/pagseguro/pagseguro.py
src/getpaid/pagseguro/tests.py
src/getpaid/pagseguro/browser/__init__.py
src/getpaid/pagseguro/browser/getpaidthankyou.py
src/getpaid/pagseguro/browser/overrides.zcml
src/getpaid/pagseguro/browser/pagsegurobutton.py
src/getpaid/pagseguro/browser/templates/pagsegurobutton.pt
src/getpaid/pagseguro/browser/templates/pagsegurothankyou.pt
src/getpaid/pagseguro/ipn/__init__.py
src/getpaid/pagseguro/ipn/configure.zcml
src/getpaid/pagseguro/ipn/notification.py
src/getpaid/pagseguro/ipn/submit_handler.py
src/getpaid/pagseguro/ipn/templates/ipnlistener.pt
src/getpaid/pagseguro/locales/empty.pt
src/getpaid/pagseguro/locales/getpaid.pagseguro.pot
src/getpaid/pagseguro/locales/getpaid.paypal.pot
src/getpaid/pagseguro/locales/manual.pot
src/getpaid/pagseguro/locales/en/LC_MESSAGES/getpaid.pagseguro.mo
src/getpaid/pagseguro/locales/en/LC_MESSAGES/getpaid.pagseguro.po
src/getpaid/pagseguro/locales/es/LC_MESSAGES/getpaid.pagseguro.mo
src/getpaid/pagseguro/locales/es/LC_MESSAGES/getpaid.pagseguro.po
src/getpaid/pagseguro/locales/it/LC_MESSAGES/getpaid.pagseguro.mo
src/getpaid/pagseguro/locales/it/LC_MESSAGES/getpaid.pagseguro.po
src/getpaid/pagseguro/locales/nl/LC_MESSAGE/getpaid.pagseguro.mo
src/getpaid/pagseguro/locales/nl/LC_MESSAGE/getpaid.pagseguro.po
src/getpaid/pagseguro/locales/pt_BR/LC_MESSAGES/getpaid.pagseguro.mo
src/getpaid/pagseguro/locales/pt_BR/LC_MESSAGES/getpaid.pagseguro.po