Metadata-Version: 1.0
Name: getpaid.pagseguro
Version: 0.1dev
Summary: Get Paid payment processor for pagseguro
Home-page: http://www.plonegetpaid.com/
Author: Get Paid Development Team and Cooperativa Inverta
Author-email: rafael@inverta.com.br
License: ZPL2.1
Keywords: getpaid processor pagseguro
Platform: UNKNOWN
Classifier: Framework :: Plone
Classifier: Framework :: Zope3
Classifier: Programming Language :: Python
Classifier: Intended Audience :: Developers
Classifier: Topic :: Software Development :: Libraries :: Python Modules
Classifier: Topic :: Office/Business :: Financial
Classifier: Topic :: Software Development :: Libraries
Classifier: License :: OSI Approved :: Zope Public License
Classifier: Operating System :: OS Independent
